CHANGES.rst
MANIFEST.in
README.rst
setup.cfg
setup.py
collective/__init__.py
collective.behavior.sql.egg-info/PKG-INFO
collective.behavior.sql.egg-info/SOURCES.txt
collective.behavior.sql.egg-info/dependency_links.txt
collective.behavior.sql.egg-info/entry_points.txt
collective.behavior.sql.egg-info/namespace_packages.txt
collective.behavior.sql.egg-info/not-zip-safe
collective.behavior.sql.egg-info/requires.txt
collective.behavior.sql.egg-info/top_level.txt
collective/behavior/__init__.py
collective/behavior/sql/__init__.py
collective/behavior/sql/configure.zcml
collective/behavior/sql/content.py
collective/behavior/sql/indexers.py
collective/behavior/sql/indexers.zcml
collective/behavior/sql/interfaces.py
collective/behavior/sql/monkeypatch.py
collective/behavior/sql/monkeypatch.zcml
collective/behavior/sql/ordering.py
collective/behavior/sql/profiles.zcml
collective/behavior/sql/setuphandlers.py
collective/behavior/sql/vocabularies.py
collective/behavior/sql/vocabularies.zcml
collective/behavior/sql/behavior/__init__.py
collective/behavior/sql/behavior/behaviors.py
collective/behavior/sql/behavior/configure.zcml
collective/behavior/sql/behavior/schemaeditor.py
collective/behavior/sql/behavior/supermodel.py
collective/behavior/sql/browser/__init__.py
collective/behavior/sql/browser/add.py
collective/behavior/sql/browser/add_field.py
collective/behavior/sql/browser/behaviors.py
collective/behavior/sql/browser/configure.zcml
collective/behavior/sql/browser/data.py
collective/behavior/sql/browser/edit.py
collective/behavior/sql/browser/fields.py
collective/behavior/sql/browser/layout.py
collective/behavior/sql/browser/listing.py
collective/behavior/sql/browser/overview.py
collective/behavior/sql/browser/types.py
collective/behavior/sql/browser/templates/overview.pt
collective/behavior/sql/browser/templates/schema_listing.pt
collective/behavior/sql/browser/templates/sql_test.pt
collective/behavior/sql/locales/collective.behavior.sql.pot
collective/behavior/sql/locales/update.sh
collective/behavior/sql/locales/en/LC_MESSAGES/collective.behavior.sql.mo
collective/behavior/sql/locales/en/LC_MESSAGES/collective.behavior.sql.po
collective/behavior/sql/locales/fr/LC_MESSAGES/collective.behavior.sql.mo
collective/behavior/sql/locales/fr/LC_MESSAGES/collective.behavior.sql.po
collective/behavior/sql/profiles/default/browserlayer.xml
collective/collective.behavior.sql.egg-info/PKG-INFO
collective/collective.behavior.sql.egg-info/SOURCES.txt
collective/collective.behavior.sql.egg-info/dependency_links.txt
collective/collective.behavior.sql.egg-info/entry_points.txt
collective/collective.behavior.sql.egg-info/namespace_packages.txt
collective/collective.behavior.sql.egg-info/not-zip-safe
collective/collective.behavior.sql.egg-info/requires.txt
collective/collective.behavior.sql.egg-info/top_level.txt