Metadata-Version: 1.1
Name: collective.behavior.sql
Version: 0.9.12
Summary: collective.behavior.sql
Home-page: http://www.martronic.ch
Author: Martronic SA
Author-email: martronic@martronic.ch
License: GPL
Keywords: dexterity,behavior,sql
Platform: UNKNOWN
Classifier: Framework :: Plone
Classifier: Programming Language :: Python
Classifier: Topic :: Software Development :: Libraries :: Python Modules
